datajoint_babel/__init__.py
datajoint_babel/constants.py
datajoint_babel/exceptions.py
datajoint_babel/model/__init__.py
datajoint_babel/model/attribute.py
datajoint_babel/model/schema.py
datajoint_babel/model/table.py
datajoint_babel/model.py
datajoint_babel/spawn.py
datajoint_babel-0.1.9.dist-info/LICENSE
datajoint_babel-0.1.9.dist-info/WHEEL
datajoint_babel-0.1.9.dist-info/METADATA
datajoint_babel-0.1.9.dist-info/RECORD
