Metadata-Version: 2.1
Name: datajoint-babel
Version: 0.1.9
Summary: Generate schema code from model definitions for both Python and MATLAB
Home-page: https://github.com/auto-pi-lot/datajoint-babel
License: MPL-2.0
Keywords: datajoint,interoperability,code generation
Author: sneakers-the-rat
Author-email: JLSaunders987@gmail.com
Requires-Python: >=3.7,<4.0
Classifier: Development Status :: 2 - Pre-Alpha
Classifier: Intended Audience :: Science/Research
Classifier: License :: OSI Approved
Classifier: License :: OSI Approved :: Mozilla Public License 2.0 (MPL 2.0)
Classifier: Natural Language :: English
Classifier: Operating System :: OS Independent
Classifier: Programming Language :: Python :: 3
Classifier: Programming Language :: Python :: 3 :: Only
Classifier: Programming Language :: Python :: 3.10
Classifier: Programming Language :: Python :: 3.11
Classifier: Programming Language :: Python :: 3.7
Classifier: Programming Language :: Python :: 3.8
Classifier: Programming Language :: Python :: 3.9
Classifier: Topic :: Software Development :: Code Generators
Requires-Dist: datajoint (>=0.13.4,<0.14.0)
Requires-Dist: parse (>=1.19.0,<2.0.0)
Requires-Dist: pydantic (>=1.9.0,<2.0.0)
Project-URL: Repository, https://github.com/auto-pi-lot/datajoint-babel
